.gitignore
pyctl.c
setup.py
debian/README
debian/changelog
debian/compat
debian/control
debian/copyright
debian/docs
debian/rules
debian/source/format
nicos_pyctl.egg-info/PKG-INFO
nicos_pyctl.egg-info/SOURCES.txt
nicos_pyctl.egg-info/dependency_links.txt
nicos_pyctl.egg-info/top_level.txt
nicospyctl/__init__.py