Metadata-Version: 2.1
Name: nicos-pyctl
Version: 1.3
Summary: NICOS pyctl c module
Home-page: https://forge.frm2.tum.de/simple/nicos-pyctl/
Author: Georg Brandl
Author-email: georg.brandl@frm2.tum.de
